pytyped/hocon/__init__.py
pytyped/hocon/parser.py
pytyped/hocon/py.typed
pytyped_hocon-1.0.0.dist-info/LICENSE
pytyped_hocon-1.0.0.dist-info/METADATA
pytyped_hocon-1.0.0.dist-info/WHEEL
pytyped_hocon-1.0.0.dist-info/top_level.txt
pytyped_hocon-1.0.0.dist-info/RECORD
